vector_materials/__init__.py
vector_materials/data_preparation.py
vector_materials/data_visualisation.py
vector_materials-0.1.2.dist-info/LICENSE
vector_materials-0.1.2.dist-info/METADATA
vector_materials-0.1.2.dist-info/WHEEL
vector_materials-0.1.2.dist-info/RECORD
